pyproject_dependencies/__init__.py
pyproject_dependencies/__main__.py
pyproject_dependencies/compat.py
pyproject_dependencies-1.3.2.dist-info/METADATA
pyproject_dependencies-1.3.2.dist-info/WHEEL
pyproject_dependencies-1.3.2.dist-info/entry_points.txt
pyproject_dependencies-1.3.2.dist-info/licenses/LICENSE
pyproject_dependencies-1.3.2.dist-info/RECORD
