Metadata-Version: 2.1
Name: pyproject-dependencies
Version: 1.3.2
Project-URL: Homepage, https://github.com/sbidoul/pyproject-dependencies
Author-email: Stéphane Bidoul <stephane.bidoul@gmail.com>
License-File: LICENSE
Classifier: Development Status :: 4 - Beta
Classifier: License :: OSI Approved :: MIT License
Requires-Python: >=3.7
Requires-Dist: build
Requires-Dist: packaging
Requires-Dist: tomli; python_version < '3.11'
Requires-Dist: typing-extensions; python_version < '3.8'
Provides-Extra: test
Requires-Dist: coverage[toml]; extra == 'test'
Requires-Dist: mypy; extra == 'test'
Requires-Dist: pytest; extra == 'test'
Requires-Dist: pytest-cov; extra == 'test'
